imagerotation
