Metadata-Version: 1.2
Name: imagerotation
Version: 2.0.0
Summary: It will rotate image by a specific angle provided by user
Home-page: UNKNOWN
Author: Dibya Raj Ghosh
Author-email: dibyaraj11@gmail.com
Maintainer: Dibya
Maintainer-email: dibyaraj11@gmail.com
License: MIT
Platform: UNKNOWN
